metadsl/__init__.py
metadsl/dict_tools.py
metadsl/expressions.py
metadsl/expressions_test.py
metadsl/logging.py
metadsl/module_tools.py
metadsl/normalized.py
metadsl/normalized_test.py
metadsl/typing_tools.py
metadsl/typing_tools_test.py
metadsl-0.4.0.dist-info/WHEEL
metadsl-0.4.0.dist-info/METADATA
metadsl-0.4.0.dist-info/RECORD
